jivago/__init__.py
jivago/jivago_application.py
jivago/py.typed
jivago/config/__init__.py
jivago/config/abstract_binder.py
jivago/config/abstract_context.py
jivago/config/debug_jivago_context.py
jivago/config/exception_mapper_binder.py
jivago/config/production_jivago_context.py
jivago/config/startup_hooks.py
jivago/config/properties/__init__.py
jivago/config/properties/application_config_loader.py
jivago/config/properties/application_properties.py
jivago/config/properties/exception.py
jivago/config/properties/global_config_loader.py
jivago/config/properties/json_config_loader.py
jivago/config/properties/system_environment_properties.py
jivago/config/properties/yaml_config_loader.py
jivago/config/router/__init__.py
jivago/config/router/cors_rule.py
jivago/config/router/router_builder.py
jivago/config/router/router_config_rule.py
jivago/config/router/filtering/__init__.py
jivago/config/router/filtering/annotation.py
jivago/config/router/filtering/auto_discovering_filtering_rule.py
jivago/config/router/filtering/filtering_rule.py
jivago/event/__init__.py
jivago/event/async_event_bus.py
jivago/event/event_bus.py
jivago/event/synchronous_event_bus.py
jivago/event/config/__init__.py
jivago/event/config/annotations.py
jivago/event/config/reflective_event_bus_initializer.py
jivago/event/config/runnable_event_handler_binder.py
jivago/event/dispatch/__init__.py
jivago/event/dispatch/jit_message_dispatcher_class.py
jivago/event/dispatch/message_dispatcher.py
jivago/event/dispatch/message_dispatcher_class.py
jivago/event/dispatch/message_dispatcher_function.py
jivago/event/dispatch/message_dispatcher_runnable.py
jivago/inject/__init__.py
jivago/inject/annotation.py
jivago/inject/annoted_class_binder.py
jivago/inject/provider_binder.py
jivago/inject/service_locator.py
jivago/inject/typing_meta_helper.py
jivago/inject/exception/__init__.py
jivago/inject/exception/instantiation_exception.py
jivago/inject/exception/non_injectable_constructor_exception.py
jivago-0.6.5.dist-info/LICENSE
jivago-0.6.5.dist-info/METADATA
jivago-0.6.5.dist-info/WHEEL
jivago-0.6.5.dist-info/top_level.txt
jivago-0.6.5.dist-info/RECORD
