Metadata-Version: 2.1
Name: jivago
Version: 0.6.5
Summary: The highly-reflective object-oriented Python web framework
Home-page: https://github.com/keotl/jivago
Author: Kento A. Lauzon
Author-email: kento.lauzon@ligature.ca
Classifier: Development Status :: 4 - Beta
Classifier: Intended Audience :: Developers
Classifier: Topic :: Software Development :: Libraries :: Application Frameworks
Classifier: License :: OSI Approved :: MIT License
Classifier: Programming Language :: Python :: 3.7
Classifier: Programming Language :: Python :: 3.8
Classifier: Programming Language :: Python :: 3.9
Classifier: Programming Language :: Python :: 3.10
Classifier: Programming Language :: Python :: 3.11
License-File: LICENSE
Requires-Dist: Jinja2
Requires-Dist: croniter
Requires-Dist: pyyaml
Requires-Dist: werkzeug
